pyq/__init__.py
pyq/__main__.py
pyq/cli.py
pyq/expr.py
python_pyq-0.0.4.dist-info/METADATA
python_pyq-0.0.4.dist-info/WHEEL
python_pyq-0.0.4.dist-info/entry_points.txt
python_pyq-0.0.4.dist-info/top_level.txt
python_pyq-0.0.4.dist-info/RECORD
