Metadata-Version: 2.1
Name: python-pyq
Version: 0.0.4
Summary: Pipe stdout to python
Home-page: https://github.com/piotrszyma/pyq
Author: Piotr Szyma
Author-email: contact@piotrszyma.pl
License: MIT
Platform: UNKNOWN
Classifier: License :: OSI Approved :: MIT License
Classifier: Programming Language :: Python :: 3
Classifier: Programming Language :: Python :: 3.10
